timesfm/__init__.py
timesfm/data_loader.py
timesfm/patched_decoder.py
timesfm/time_features.py
timesfm/timesfm.py
timesfm/xreg_lib.py
timesfm_jax-1.0.1.dist-info/LICENSE
timesfm_jax-1.0.1.dist-info/METADATA
timesfm_jax-1.0.1.dist-info/WHEEL
timesfm_jax-1.0.1.dist-info/top_level.txt
timesfm_jax-1.0.1.dist-info/RECORD
